Workbook

Sheet 5.1 - Investimentos fixos
A1: A) Máquinas e equipamentos
B2: Descrição | C2: Qtde. | D2: Valor unitário | E2: Total
A3: 1 | B3: Servidor | C3: 1 | D3: 35000 | E3: =C3*D3 -> 35000
A4: 2 | B4: Software | C4: 1 | D4: 10000 | E4: =C4*D4 -> 10000
A5: 3 | B5: Nobreak | C5: 2 | D5: 2200 | E5: =C5*D5 -> 4400
A6: 4 | B6: Notebook | C6: 5 | D6: 2800 | E6: =C6*D6 -> 14000
A7: 5 | B7: Impressora | C7: 1 | D7: 2500 | E7: =C7*D7 -> 2500
A8: 6 | B8: Roteador | C8: 1 | D8: 7000 | E8: =C8*D8 -> 7000
A9: 7 | B9: TV/Monitor | C9: 10 | D9: 790 | E9: =C9*D9 -> 7900
A10: Sub-total | E10: =SUM(E3:E9) -> 80800
A11: B) Móveis e utensílios
B12: Descrição | C12: Qtde. | D12: Valor unitário | E12: Total
A13: 1 | B13: TELEVISÃO | C13: 3 | D13: 2200 | E13: =C13*D13 -> 6600
A14: 2 | B14: MESA DE CAFÉ | C14: 2 | D14: 200 | E14: 200
A15: 3 | B15: RACK DE SERVIDOR | C15: 1 | D15: 1500 | E15: =C15*D15 -> 1500
A16: 4 | B16: BALCÃO DE RECEPÇÃO | C16: 1 | D16: 1800 | E16: =C16*D16 -> 1800
A17: 5 | B17: Mesa de Trabalho | C17: 5 | D17: 400 | E17: =C17*D17 -> 2000
A18: 6 | B18: Mesa de reunião | C18: 1 | D18: 1500 | E18: =C18*D18 -> 1500
A19: 7 | B19: Cadeiras | C19: 12 | D19: 450 | E19: =C19*D19 -> 5400
A20: 8 | B20: Armário | C20: 6 | D20: 800 | E20: =C20*D20 -> 4800
A21: Sub-total | E21: =SUM(E13:E20) -> 23800
A22: C) Veículos/ Imóveis
B23: Descrição | C23: Qtde. | D23: Valor unitário | E23: Total
A24: 1 | B24: Carro | C24: 1 | D24: 35000 | E24: =D24*C24 -> 35000
A25: 2 | E25: =D25*C25 -> 0
A26: Sub-total | E26: =SUM(E24:E25) -> 35000
A27: Total de Investimentos Fixos | D27: Sub-total | E27: =SUM(E10,E21,E26) -> 139600

Sheet 5.2.0 - Estoque inicial
A1: A) Estimativa de Estoque inicial
B2: Descrição | C2: Qtde. | D2: Valor unitário | E2: Total
A3: 1 | B3: Resmas de papel A4 | C3: 10 | D3: 25 | E3: =D3*C3 -> 250
A4: 2 | B4: Canetas esferográficas (un) | C4: 50 | D4: 1.5 | E4: =D4*C4 -> 75
A5: 3 | B5: lapiseiras (un) | C5: 30 | D5: 1.5 | E5: =D5*C5 -> 45
A6: 4 | B6: Caixas de clips para papel (caixa) | C6: 10 | D6: 20 | E6: =D6*C6 -> 200
A7: 5 | B7: Grampeador (un) | C7: 5 | D7: 20 | E7: =D7*C7 -> 100
A8: 6 | B8: Recarga de grampos para grampeador(caixa) | C8: 10 | D8: 15 | E8: =D8*C8 -> 150
A9: 7 | B9: Pastas de Arquivo (un) | C9: 20 | D9: 25 | E9: =D9*C9 -> 500
A10: 8 | B10: Blocos adesivos para anotações (blocos) | C10: 15 | D10: 5 | E10: =D10*C10 -> 75
A11: 9 | B11: Fita Adesiva (rolo) | C11: 10 | D11: 4 | E11: =D11*C11 -> 40
A12: 10 | B12: Bloco de Notas (bloco) | C12: 10 | D12: 7 | E12: =D12*C12 -> 70
A13: Sub-total | E13: =SUM(E3:E12) -> 1505

Sheet 5.2.1 - Caixa mínimo
A1: Prazo médio de vendas | B1: % | C1: Número de dias | D1: Média Ponderada | G1: Número de dias
A2: a vista | B2: 1 | C2: 30 | D2: =C2*B2 -> 30 | F2: Recursos da empresa fora do seu caixa
A3: a prazo (1) | D3: =C3*B3 -> 0 | F3: 1. Contas a Receber – prazo médio de vendas | G3: =D8 -> 30
A4: a prazo (2) | D4: =C4*B4 -> 0 | F4: 2. Estoques – necessidade média de estoques | G4: =B20
A5: a prazo (3) | D5: =C5*B5 -> 0 | F5: Subtotal 1 (item 1+2) | G5: =SUM(G3:G4) -> 30
A6: a prazo (4) | D6: =C6*B6 -> 0 | F6: Recursos de terceiros no caixa da empresa
A7: a prazo (5) | D7: =C7*B7 -> 0 | F7: 3. Fornecedores – prazo médio de compras | G7: =D17 -> 30
A8: Prazo médio total (dias) | D8: =SUM(D2:D7) -> 30 | F8: Subtotal 2 | G8: =G7 -> 30
F9: Necessidade Líquida de Capital de Giro em dias | G9: =G5-G8 -> 0
A10: Prazo médio de compras | B10: % | C10: Número de dias | D10: Média Ponderada
A11: a vista | B11: 1 | C11: 30 | D11: =C11*B11 -> 30 | F11: B) Caixa mínimo
A12: a prazo (1) | D12: =C12*B12 -> 0 | F12: 1. Custo fixo mensal (Quadro 5.11) | G12: ='5.11 - custos fixos operacionai'!B19 -> 313887.36
A13: a prazo (2) | D13: =C13*B13 -> 0 | F13: 2. Custo variável mensal (Subtotal 2 do quadro 5.12) | G13: =-'5.12 - Demonstrativo de Resulta'!C4 -> 84596.407
A14: a prazo (3) | D14: =C14*B14 -> 0 | F14: 3. Custo total da empresa (item 1 + 2) | G14: =SUM(G12:G13) -> 398483.77
A15: a prazo (4) | D15: =C15*B15 -> 0 | F15: 4. Custo total diário (item 3 ÷ 30 dias) | G15: =G14/30 -> 13282.792
A16: a prazo (5) | D16: =C16*B16 -> 0 | F16: 5. Necessidade Líquida de Capital de Giro em dias | G16: =G9 -> 0
A17: Prazo médio total (dias) | D17: =SUM(D11:D16) -> 30 | F17: Total de B – Caixa mínimo (item 4 x 5) | G17: =G15*G16 -> 0
B19: Número de dias
A20: Necessidade média de estoque

Sheet 5.2 - Capital de giro
A1: Capital de giro | B1: R$
A2: A – Estoque inicial | B2: ='5.2.0 - Estoque inicial'!E13 -> 1505
A3: B – Caixa mínimo | B3: ='5.2.1 - Caixa mínimo'!G17 -> 0
A4: Total do capital de giro (A +B) | B4: =SUM(B2:B3) -> 1505

Sheet 5.3 - Investimentos pré-operaci
A1: Investimento pré-operacional | B1: R$
A2: Despesas de legalização | B2: 1600
A3: Obras civis e ou reforma | B3: 3000
A4: Divulgação | B4: 1500
A5: Cursos e treinamentos | B5: 9000
A6: Outras despesas
A7: Total | B7: =SUM(B2:B6) -> 15100

Sheet 5.4 - Investimento total (resum
A1: Descrição dos investimentos | B1: Valor (R$) | C1: (%)
A2: 1. Investimento fixo | B2: ='5.1 - Investimentos fixos'!E27 -> 139600 | C2: =B2/SUM($B$2:$B$4) -> 0.89369738
A3: 2. Capital de Giro | B3: ='5.2 - Capital de giro'!B4 -> 1505 | C3: =B3/SUM($B$2:$B$4) -> 0.0096347748
A4: 3. Investimento pré-operacional | B4: ='5.3 - Investimentos pré-operaci'!B7 -> 15100 | C4: =B4/SUM($B$2:$B$4) -> 0.09666784
A5: Total (1+2+3) | B5: =SUM(B2:B4) -> 156205 | C5: =SUM(C2:C4) -> 1
A7: Fontes de recursos | B7: Valor (R$) | C7: (%)
A8: 1. Recursos próprios | B8: 139600 | C8: =B8/SUM($B$8:$B$10) -> 1
A9: 2. Recursos de terceiros | C9: =B9/SUM($B$8:$B$10) -> 0
A10: 3. Outros | C10: =B10/SUM($B$8:$B$10) -> 0
A11: Total (1+2+3) | B11: =SUM(B8:B10) -> 139600 | C11: =SUM(C8:C10) -> 1

Sheet 5.5 – Estimativa do faturamento
A1: Produto/ Serviço | B1: Quantidade (Estimativa de Vendas) | C1: Preço de Venda Unitário (em R$) | D1: Faturamento Total (em R$)
A2: Assinatura anual | B2: 4680 | C2: 89.9 | D2: =B2*C2 -> 420732
A3: 2 | D3: =B3*C3 -> 0
A4: 3 | D4: =B4*C4 -> 0
A5: 4 | D5: =B5*C5 -> 0
A6: 5 | D6: =B6*C6 -> 0
A7: Total | D7: =SUM(D2:D6) -> 420732

Sheet 5.6 - Estimativa custos comerci
A1: Produto/ Serviço 1
A2: Material/insumos | B2: Qtd. | C2: Custo Unitário (R$) | D2: Total (R$)
D3: =B3*C3 -> 0
D4: =B4*C4 -> 0
D5: =B5*C5 -> 0
D6: =B6*C6 -> 0
D7: =B7*C7 -> 0
D8: =B8*C8 -> 0
A9: Total | D9: =SUM(D3:D8) -> 0
A11: Produto/ Serviço 2
A12: Material/insumos | B12: Qtd. | C12: Custo Unitário (R$) | D12: Total (R$)
D13: =B13*C13 -> 0
D14: =B14*C14 -> 0
D15: =B15*C15 -> 0
D16: =B16*C16 -> 0
D17: =B17*C17 -> 0
D18: =B18*C18 -> 0
A19: Total | D19: =SUM(D13:D18) -> 0

Sheet 5.7 – Estimativa dos custos de
A1: Descrição | B1: (%) | C1: Faturamento estimando | D1: Custo total
A2: 1. Imposto
A3: Impostos Federais
A4: SIMPLES | B4: 0.195 | C4: ='5.5 – Estimativa do faturamento'!$D$7 -> 420732 | D4: =(C4*B4)-9900 -> 72142.74
A5: IRPJ | C5: ='5.5 – Estimativa do faturamento'!$D$7 -> 420732 | D5: =C5*B5 -> 0
A6: PIS | C6: ='5.5 – Estimativa do faturamento'!$D$7 -> 420732 | D6: =C6*B6 -> 0
A7: COFINS | C7: ='5.5 – Estimativa do faturamento'!$D$7 -> 420732 | D7: =C7*B7 -> 0
A8: CSLL | C8: ='5.5 – Estimativa do faturamento'!$D$7 -> 420732 | D8: =C8*B8 -> 0
A9: Impostos Estaduais
A10: ICMS | C10: ='5.5 – Estimativa do faturamento'!$D$7 -> 420732 | D10: =C10*B10 -> 0
A11: Impostos Municipais
A12: ISS | C12: ='5.5 – Estimativa do faturamento'!$D$7 -> 420732 | D12: =C12*B12 -> 0
A13: Subtotal 1 | D13: =SUM(D4:D8,D10,D12) -> 72142.74
A14: 2. Gastos com vendas
A15: Comissões | C15: ='5.5 – Estimativa do faturamento'!$D$7 -> 420732 | D15: =C15*B15 -> 0
A16: Propaganda | C16: ='5.5 – Estimativa do faturamento'!$D$7 -> 420732 | D16: =C16*B16 -> 0
A17: Taxa de cartão de crédito | B17: 0.0296 | C17: ='5.5 – Estimativa do faturamento'!$D$7 -> 420732 | D17: =C17*B17 -> 12453.667
A18: Subtotal 2 | D18: =SUM(D15:D17) -> 12453.667
A19: TOTAL (Subtotal 1+ 2) | D19: =SUM(D18,D13) -> 84596.407

Sheet 5.8 - CMD CMV
A1: Produto/ Serviço | B1: Estimativa de Vendas (em unidade) | C1: Custo Unitário de Materiais/ Aquisição (R$) | D1: CMD/CMV (R$)
A2: 1 | D2: =B2*C2 -> 0
A3: 2 | D3: =B3*C3 -> 0
A4: 3 | D4: =B4*C4 -> 0
A5: 4 | D5: =B5*C5 -> 0
A6: 5 | D6: =B6*C6 -> 0
A7: 6 | D7: =B7*C7 -> 0
A8: Total | D8: =SUM(D2:D7) -> 0

Sheet 5.9 - Mão de obra
A1: Função | B1: Nº de empregados | C1: Salario mensal (R$) | D1: (%) de encargos sociais | E1: Encargos sociais (R$) | F1: Total (R$)
A2: Administrador de banco de dados | B2: 1 | C2: 3943.65 | D2: 0.7 | E2: =C2*D2 -> 2760.555 | F2: =B2*(SUM(C2,E2)) -> 6704.205
A3: Administrador de Redes | B3: 1 | C3: 3659 | D3: 0.7 | E3: =C3*D3 -> 2561.3 | F3: =B3*(SUM(C3,E3)) -> 6220.3
A4: Analista de sistemas | B4: 1 | C4: 3508.1 | D4: 0.7 | E4: =C4*D4 -> 2455.67 | F4: =B4*(SUM(C4,E4)) -> 5963.77
E5: =C5*D5 -> 0 | F5: =B5*(SUM(C5,E5)) -> 0
E6: =C6*D6 -> 0 | F6: =B6*(SUM(C6,E6)) -> 0
A7: Total | F7: =SUM(F2:F6) -> 18888.275

Sheet 5.11 - custos fixos operacionai
A1: Descrição | B1: Custo Total Mensal (em R$)
A2: Aluguel | B2: 0
A3: Condomínio | B3: 0
A4: IPTU | B4: 0
A5: Água | B5: 0
A6: Energia Elétrica | B6: 0
A7: Telefone | B7: 89
A8: Honorários do Contador | B8: 350
A9: Pró-labore | B9: 6000
A10: Manutenção de equipamentos | B10: 100
A11: Salários + encargos (Anexo 2) | B11: 18888.28
A12: Material de Limpeza | B12: 40
A13: Material de Escritório | B13: 30
... A18: Treinamento | B18: 350
A19: Total | B19: =SUM(B2:B18)*12 -> 313887.36

Sheet 5.12 - Demonstrativo de Resulta
A2: Quadro | B2: Descrição
A3: 5.5 | B3: 1. Receita total com vendas | C3: ='5.5 – Estimativa do faturamento'!D7 -> 420732
B4: 2. Custos variáveis totais | C4: =SUM(C5:C7) -> -84596.407
A5: 5.8 | B5: (-) CMV(*) | C5: =-'5.8 - CMD CMV'!D8 -> 0
A6: 5.7 | B6: (-) Impostos sobre venda | C6: =-'5.7 – Estimativa dos custos de'!D13 -> -72142.74
A7: 5.7 | B7: (-) Gastos com vendas | C7: =-'5.7 – Estimativa dos custos de'!D18 -> -12453.667
B8: Subtotal 2 | C8: =C4 -> -84596.407
B9: 3. Margem de Contribuição | C9: =C3+C4 -> 336135.59
A10: 5.11 | B10: 4. (-) Custos fixos totais | C10: =-'5.11 - custos fixos operacionai'!B19 -> -313887.36
B11: Resultado operacional | C11: =C9+C10 -> 22248.233

Sheet 5.13.1 – Ponto de equilíbrio
A1: Receita total | B1: =SUM('5.12 - Demonstrativo de Resulta'!C3) -> 420732
A2: Custo variavel total | B2: =-SUM('5.12 - Demonstrativo de Resulta'!C4) -> 84596.407
A3: Custo fixo total | B3: =-SUM('5.12 - Demonstrativo de Resulta'!C10) -> 313887.36
A4: Índice da Margem de Contribuição | B4: =(B1-B2)/B1 -> 0.79893042
A5: Ponto de equilíbrio | B5: =B3/B4 -> 392884.48

Sheet 5.13.2 – Lucratividade
A1: Lucro Líquido | B1: =SUM('5.12 - Demonstrativo de Resulta'!C11) -> 22248.233
A2: Receita Total | B2: =SUM('5.12 - Demonstrativo de Resulta'!C3) -> 420732
A3: Lucratividade | B3: =(B1/B2) -> 0.052879821

Sheet 5.13.3. Rentabilidade
A1: Lucro Líquido | B1: =SUM('5.12 - Demonstrativo de Resulta'!C11) -> 22248.233
A2: Investimento Total | B2: ='5.4 - Investimento total (resum'!B11 -> 139600
A3: Rentabilidade | B3: =B1/B2 -> 0.1593713

Sheet 5.13.4 – Prazo de retorno do in
A1: Investimento Total | B1: ='5.4 - Investimento total (resum'!B11 -> 139600
A2: Lucro Líquido | B2: =SUM('5.12 - Demonstrativo de Resulta'!C11) -> 22248.233
A3: Retorno do Investimento | B3: =B1/B2 -> 6.2746557 | C3: 6 meses
B6: 22248.23 | C6: 12
B7: 100 | C7: x
B8: =B7*C6 -> 1200
B9: =B8/B6 -> 0.053936875
